odoo/addons/project_template/README.rst
odoo/addons/project_template/__init__.py
odoo/addons/project_template/__manifest__.py
odoo/addons/project_template/i18n/es.po
odoo/addons/project_template/i18n/fr.po
odoo/addons/project_template/i18n/it.po
odoo/addons/project_template/i18n/project_template.pot
odoo/addons/project_template/i18n/pt.po
odoo/addons/project_template/i18n/sl.po
odoo/addons/project_template/models/__init__.py
odoo/addons/project_template/models/project.py
odoo/addons/project_template/readme/CONTRIBUTORS.rst
odoo/addons/project_template/readme/DESCRIPTION.rst
odoo/addons/project_template/readme/USAGE.rst
odoo/addons/project_template/static/description/icon.png
odoo/addons/project_template/static/description/index.html
odoo/addons/project_template/tests/__init__.py
odoo/addons/project_template/tests/test_project_template.py
odoo/addons/project_template/views/project.xml
odoo11_addon_project_template-11.0.1.0.1.99.dev4.dist-info/METADATA
odoo11_addon_project_template-11.0.1.0.1.99.dev4.dist-info/WHEEL
odoo11_addon_project_template-11.0.1.0.1.99.dev4.dist-info/top_level.txt
odoo11_addon_project_template-11.0.1.0.1.99.dev4.dist-info/RECORD
